CHANGES.rst
CONTRIBUTORS.rst
MANIFEST.in
README.rst
requirements.txt
setup.cfg
setup.py
docs/LICENSE.GPL
docs/LICENSE.rst
docs/index.rst
src/kitconcept/__init__.py
src/kitconcept.voltodemo.egg-info/PKG-INFO
src/kitconcept.voltodemo.egg-info/SOURCES.txt
src/kitconcept.voltodemo.egg-info/dependency_links.txt
src/kitconcept.voltodemo.egg-info/entry_points.txt
src/kitconcept.voltodemo.egg-info/namespace_packages.txt
src/kitconcept.voltodemo.egg-info/not-zip-safe
src/kitconcept.voltodemo.egg-info/requires.txt
src/kitconcept.voltodemo.egg-info/top_level.txt
src/kitconcept/voltodemo/__init__.py
src/kitconcept/voltodemo/configure.zcml
src/kitconcept/voltodemo/controlpanel.py
src/kitconcept/voltodemo/interfaces.py
src/kitconcept/voltodemo/patches.py
src/kitconcept/voltodemo/setuphandlers.py
src/kitconcept/voltodemo/testing.py
src/kitconcept/voltodemo/upgrades.zcml
src/kitconcept/voltodemo/cors/__init__.py
src/kitconcept/voltodemo/cors/configure.zcml
src/kitconcept/voltodemo/profiles/default/browserlayer.xml
src/kitconcept/voltodemo/profiles/default/controlpanel.xml
src/kitconcept/voltodemo/profiles/default/metadata.xml
src/kitconcept/voltodemo/profiles/default/registry.xml
src/kitconcept/voltodemo/profiles/default/types.xml
src/kitconcept/voltodemo/profiles/default/types/Document.xml
src/kitconcept/voltodemo/profiles/default/types/Event.xml
src/kitconcept/voltodemo/profiles/default/types/Plone_Site.xml
src/kitconcept/voltodemo/profiles/uninstall/browserlayer.xml
src/kitconcept/voltodemo/tests/__init__.py
src/kitconcept/voltodemo/tests/test_setup.py